gdrive_core/__init__.py
gdrive_core/core.py
gdrive_core-1.6.dist-info/METADATA
gdrive_core-1.6.dist-info/WHEEL
gdrive_core-1.6.dist-info/top_level.txt
gdrive_core-1.6.dist-info/RECORD
