Metadata-Version: 2.1
Name: gdrive-core
Version: 1.6
Summary: A minimal, functional Google Drive API wrapper.
Home-page: https://github.com/YourAverageDev/gdrive-core
Author: YourAverageDev
Classifier: Programming Language :: Python :: 3
Classifier: Programming Language :: Python :: 3.6
Classifier: Programming Language :: Python :: 3.7
Classifier: Programming Language :: Python :: 3.8
Classifier: Programming Language :: Python :: 3.9
Classifier: Programming Language :: Python :: 3.10
Classifier: Programming Language :: Python :: 3.11
Classifier: Programming Language :: Python :: 3.12
Classifier: Operating System :: OS Independent
Requires-Python: >=3.6
Requires-Dist: google-auth
Requires-Dist: google-auth-oauthlib
Requires-Dist: google-api-python-client
